pdbutil/__init__.py
pdbutil/fasta_io.py
pdbutil/main.py
pdbutil/pdb_io.py
pdbutil/pdbio.py
pdbutil/protein_constants.py
pdbutil/rmsd.py
pdbutil/devel/geometry.py
pdbutil/devel/old.py
pdbutil-2.1.3.dist-info/LICENSE
pdbutil-2.1.3.dist-info/METADATA
pdbutil-2.1.3.dist-info/WHEEL
pdbutil-2.1.3.dist-info/entry_points.txt
pdbutil-2.1.3.dist-info/top_level.txt
pdbutil-2.1.3.dist-info/RECORD
