Metadata-Version: 2.2
Name: pdbutil
Version: 2.1.3
Summary: A simple module for handling protein backbone coordinates.
Home-page: https://github.com/ShintaroMinami/pdbutil
Author: Shintaro Minami
Author-email: shintaro.minami@gmail.com
License: MIT
Keywords: pdb,backbone
Classifier: License :: OSI Approved :: MIT License
Classifier: Programming Language :: Python :: 3
License-File: LICENSE
Requires-Dist: numpy
Requires-Dist: biopython
Dynamic: author
Dynamic: author-email
Dynamic: classifier
Dynamic: description
Dynamic: description-content-type
Dynamic: home-page
Dynamic: keywords
Dynamic: license
Dynamic: requires-dist
Dynamic: summary
